crudtape/__init__.py
crudtape/errors.py
crudtape/store.py
crudtape-0.1.4.dist-info/METADATA
crudtape-0.1.4.dist-info/WHEEL
crudtape-0.1.4.dist-info/licenses/LICENSE
crudtape-0.1.4.dist-info/RECORD
