Metadata-Version: 2.4
Name: crudtape
Version: 0.1.4
Summary: Simple in-memory CRUD store for rapid prototyping
Project-URL: Homepage, https://github.com/alesbukovsky/crudtape
Project-URL: Source, https://github.com/alesbukovsky/crudtape
Author-email: Ales Bukovsky <ales.bukovsky@gmail.com>
License-Expression: Unlicense
License-File: LICENSE
Requires-Python: >=3.8
Requires-Dist: tinydb<5.0,>=4.8.0
Provides-Extra: dev
Requires-Dist: mypy<2.0,>=0.990; extra == 'dev'
Requires-Dist: pdoc<16.0.0,>=15.0.0; extra == 'dev'
Requires-Dist: pydantic<3.0,>=2.11.0; extra == 'dev'
Requires-Dist: pytest-cov<7.0,>=6.1.0; extra == 'dev'
Requires-Dist: pytest<9.0,>=8.3.0; extra == 'dev'
Requires-Dist: ruff<2.0,>=0.0.240; extra == 'dev'
